README.md
setup.cfg
setup.py
yonwalone_dist/Binomialdistribution.py
yonwalone_dist/Gaussiandistribution.py
yonwalone_dist/Generaldistribution.py
yonwalone_dist/__init__.py
yonwalone_dist.egg-info/PKG-INFO
yonwalone_dist.egg-info/SOURCES.txt
yonwalone_dist.egg-info/dependency_links.txt
yonwalone_dist.egg-info/not-zip-safe
yonwalone_dist.egg-info/top_level.txt